[{
    "DC": 1,
    "effectivePenetration": [{
        "EPEN": 0.1,
        "physicalDamage": 0,
        "shaded": "no"
    }, {
        "EPEN": 0.2,
        "physicalDamage": 0,
        "shaded": "no"
    }, {
        "EPEN": 0.3,
        "physicalDamage": 1,
        "shaded": "no"
    }, {
        "EPEN": 0.4,
        "physicalDamage": 1,
        "shaded": "no"
    }, {
        "EPEN": 0.5,
        "physicalDamage": 1,
        "shaded": "no"
    }, {
        "EPEN": 0.6,
        "physicalDamage": 1,
        "shaded": "no"
    }]
}, {
    "DC": 2,
    "effectivePenetration": [{
        "EPEN": 0.1,
        "physicalDamage": 0,
        "shaded": "no"
    }, {
        "EPEN": 0.2,
        "physicalDamage": 1,
        "shaded": "no"
    }, {
        "EPEN": 0.3,
        "physicalDamage": 1,
        "shaded": "no"
    }, {
        "EPEN": 0.4,
        "physicalDamage": 1,
        "shaded": "no"
    }, {
        "EPEN": 0.5,
        "physicalDamage": 2,
        "shaded": "no"
    }, {
        "EPEN": 0.6,
        "physicalDamage": 3,
        "shaded": "no"
    }]
}, {
    "DC": 3,
    "effectivePenetration": [{
        "EPEN": 0.1,
        "physicalDamage": 0,
        "shaded": "no"
    }, {
        "EPEN": 0.2,
        "physicalDamage": 1,
        "shaded": "no"
    }, {
        "EPEN": 0.3,
        "physicalDamage": 2,
        "shaded": "no"
    }, {
        "EPEN": 0.4,
        "physicalDamage": 3,
        "shaded": "no"
    }, {
        "EPEN": 0.5,
        "physicalDamage": 4,
        "shaded": "no"
    }, {
        "EPEN": 0.6,
        "physicalDamage": 5,
        "shaded": "no"
    }]
}, {
    "DC": 4,
    "effectivePenetration": [{
        "EPEN": 0.1,
        "physicalDamage": 1,
        "shaded": "no"
    }, {
        "EPEN": 0.2,
        "physicalDamage": 1,
        "shaded": "no"
    }, {
        "EPEN": 0.3,
        "physicalDamage": 2,
        "shaded": "no"
    }, {
        "EPEN": 0.4,
        "physicalDamage": 4,
        "shaded": "no"
    }, {
        "EPEN": 0.5,
        "physicalDamage": 5,
        "shaded": "no"
    }, {
        "EPEN": 0.6,
        "physicalDamage": 7,
        "shaded": "no"
    }]
}, {
    "DC": 5,
    "effectivePenetration": [{
        "EPEN": 0.1,
        "physicalDamage": 1,
        "shaded": "no"
    }, {
        "EPEN": 0.2,
        "physicalDamage": 2,
        "shaded": "no"
    }, {
        "EPEN": 0.3,
        "physicalDamage": 3,
        "shaded": "no"
    }, {
        "EPEN": 0.4,
        "physicalDamage": 5,
        "shaded": "no"
    }, {
        "EPEN": 0.5,
        "physicalDamage": 7,
        "shaded": "no"
    }, {
        "EPEN": 0.6,
        "physicalDamage": 9,
        "shaded": "no"
    }]
}, {
    "DC": 6,
    "effectivePenetration": [{
        "EPEN": 0.1,
        "physicalDamage": 1,
        "shaded": "no"
    }, {
        "EPEN": 0.2,
        "physicalDamage": 2,
        "shaded": "no"
    }, {
        "EPEN": 0.3,
        "physicalDamage": 4,
        "shaded": "no"
    }, {
        "EPEN": 0.4,
        "physicalDamage": 6,
        "shaded": "no"
    }, {
        "EPEN": 0.5,
        "physicalDamage": 9,
        "shaded": "no"
    }, {
        "EPEN": 0.6,
        "physicalDamage": 11,
        "shaded": "no"
    }]
}, {
    "DC": 7,
    "effectivePenetration": [{
        "EPEN": 0.1,
        "physicalDamage": 1,
        "shaded": "no"
    }, {
        "EPEN": 0.2,
        "physicalDamage": 3,
        "shaded": "no"
    }, {
        "EPEN": 0.3,
        "physicalDamage": 6,
        "shaded": "no"
    }, {
        "EPEN": 0.4,
        "physicalDamage": 9,
        "shaded": "no"
    }, {
        "EPEN": 0.5,
        "physicalDamage": 13,
        "shaded": "no"
    }, {
        "EPEN": 0.6,
        "physicalDamage": 16,
        "shaded": "no"
    }]
}, {
    "DC": 8,
    "effectivePenetration": [{
        "EPEN": 0.1,
        "physicalDamage": 2,
        "shaded": "no"
    }, {
        "EPEN": 0.2,
        "physicalDamage": 4,
        "shaded": "no"
    }, {
        "EPEN": 0.3,
        "physicalDamage": 8,
        "shaded": "no"
    }, {
        "EPEN": 0.4,
        "physicalDamage": 12,
        "shaded": "no"
    }, {
        "EPEN": 0.5,
        "physicalDamage": 17,
        "shaded": "no"
    }, {
        "EPEN": 0.6,
        "physicalDamage": 22,
        "shaded": "no"
    }]
}, {
    "DC": 9,
    "effectivePenetration": [{
        "EPEN": 0.1,
        "physicalDamage": 2,
        "shaded": "no"
    }, {
        "EPEN": 0.2,
        "physicalDamage": 6,
        "shaded": "no"
    }, {
        "EPEN": 0.3,
        "physicalDamage": 11,
        "shaded": "no"
    }, {
        "EPEN": 0.4,
        "physicalDamage": 18,
        "shaded": "no"
    }, {
        "EPEN": 0.5,
        "physicalDamage": 26,
        "shaded": "no"
    }, {
        "EPEN": 0.6,
        "physicalDamage": 32,
        "shaded": "no"
    }]
}, {
    "DC": 10,
    "effectivePenetration": [{
        "EPEN": 0.1,
        "physicalDamage": 4,
        "shaded": "no"
    }, {
        "EPEN": 0.2,
        "physicalDamage": 9,
        "shaded": "no"
    }, {
        "EPEN": 0.3,
        "physicalDamage": 17,
        "shaded": "no"
    }, {
        "EPEN": 0.4,
        "physicalDamage": 26,
        "shaded": "no"
    }, {
        "EPEN": 0.5,
        "physicalDamage": 38,
        "shaded": "no"
    }, {
        "EPEN": 0.6,
        "physicalDamage": 47,
        "shaded": "no"
    }]
}]
